cursor_tts_mcp/__init__.py
cursor_tts_mcp/server.py
cursor_tts_mcp/templates/index.html
cursor_tts_mcp-0.1.0.dist-info/METADATA
cursor_tts_mcp-0.1.0.dist-info/WHEEL
cursor_tts_mcp-0.1.0.dist-info/entry_points.txt
cursor_tts_mcp-0.1.0.dist-info/top_level.txt
cursor_tts_mcp-0.1.0.dist-info/RECORD
