Metadata-Version: 2.2
Name: cursor-tts-mcp
Version: 0.1.0
Summary: A Text-to-Speech MCP server for Cursor IDE
Home-page: https://github.com/cursor-community/cursor-tts-mcp
Author: Cursor Community
Requires-Dist: Flask>=3.0.2
Requires-Dist: gTTS>=2.5.1
Requires-Dist: pygame>=2.5.2
Requires-Dist: python-dotenv>=1.0.1
Dynamic: author
Dynamic: description
Dynamic: description-content-type
Dynamic: home-page
Dynamic: requires-dist
Dynamic: summary
